{
  "$schema": "http://json-schema.org/draft-07/schema#",
  "$id": "http://schema.org/DryCleaningOrLaundry",
  "title": "DryCleaningOrLaundry",
  "description": "A dry-cleaning business.",
  "type": "object",
  "format": "http://schema.org/DryCleaningOrLaundry",
  "allOf": [
    {
      "description": "A particular physical business or branch of an organization. Examples of LocalBusiness include a restaurant, a particular branch of a restaurant chain, a branch of a bank, a medical practice, a club, a bowling alley, etc.",
      "$ref": "LocalBusiness.schema.json"
    }
  ],
  "properties": {
    "@context": { "const": "https://schema.org" },
    "@type": { "const": "DryCleaningOrLaundry" }
  },
  "required": ["@type"]
}
