{
  "$schema": "https://json-schema.org/draft/2020-12/schema",
  "$id": "schema:Guide",
  "title": "Guide",
  "description": "[[Guide]] is a page or article that recommend specific products or services, or aspects of a thing for a user to consider. A [[Guide]] may represent a Buying Guide and detail aspects of products or services for a user to consider. A [[Guide]] may represent a Product Guide and recommend specific products or services. A [[Guide]] may represent a Ranked List and recommend specific products or services with ranking.",
  "type": "object",
  "allOf": [
    {
      "description": "The most generic kind of creative work, including books, movies, photographs, software programs, etc.",
      "$ref": "schema:CreativeWork"
    }
  ],
  "properties": {
    "reviewAspect": {
      "description": "This Review or Rating is relevant to this part or facet of the itemReviewed.",
      "oneOf": [
        { "type": "string" },
        { "type": "array", "items": { "type": "string" } }
      ]
    }
  }
}
