{
  "$schema": "http://json-schema.org/draft-07/schema#",
  "$id": "http://schema.org/OfferItemCondition",
  "title": "OfferItemCondition",
  "description": "A list of possible conditions for the item.",
  "type": "object",
  "format": "http://schema.org/OfferItemCondition",
  "oneOf": [
    {
      "description": "Indicates that the item is damaged.",
      "const": "DamagedCondition"
    },
    {
      "description": "Indicates that the item is new.",
      "const": "NewCondition"
    },
    {
      "description": "Indicates that the item is refurbished.",
      "const": "RefurbishedCondition"
    },
    {
      "description": "Indicates that the item is used.",
      "const": "UsedCondition"
    }
  ],
  "properties": {
    "@context": { "const": "https://schema.org" },
    "@type": { "const": "OfferItemCondition" }
  },
  "required": ["@type"]
}
